ceilometer_riemann
