Metadata-Version: 1.1
Name: ceilometer-riemann
Version: 0.2.2
Summary: Riemann publisher driver for OpenStack Ceilometer
Home-page: https://github.com/briancline/ceilometer-riemann
Author: Brian Cline
Author-email: bcline@softlayer.com
License: Apache License v2.0
Keywords: ceilometer riemann metrics instrumentation stats log processing
Platform: UNKNOWN
Classifier: Development Status :: 3 - Alpha
Classifier: License :: OSI Approved :: Apache Software License
Classifier: Environment :: OpenStack
Classifier: Intended Audience :: Developers
Classifier: Intended Audience :: Information Technology
Classifier: Intended Audience :: System Administrators
Classifier: Natural Language :: English
Classifier: Operating System :: POSIX :: Linux
Classifier: Programming Language :: Python
Classifier: Programming Language :: Python :: 2.7
Classifier: Topic :: Scientific/Engineering :: Information Analysis
Classifier: Topic :: System :: Monitoring
